Metadata-Version: 2.1
Name: mysql-server-has-gone-away
Version: 2.0.0
Summary: Django myslq backend that fixes issue with long living connection
Home-page: https://github.com/akoidan/MySQL-server-has-gone-away
Author: Andrew Koidan
Author-email: deathangel908@gmail.com
License: MIT
Platform: UNKNOWN
